rkd_cooperative/__init__.py
rkd_cooperative/__main__.py
rkd_cooperative/formatting.py
rkd_cooperative/tasks.py
rkd_cooperative/test.py
rkd_cooperative-1.0.3.dist-info/AUTHORS
rkd_cooperative-1.0.3.dist-info/LICENSE
rkd_cooperative-1.0.3.dist-info/METADATA
rkd_cooperative-1.0.3.dist-info/WHEEL
rkd_cooperative-1.0.3.dist-info/entry_points.txt
rkd_cooperative-1.0.3.dist-info/pbr.json
rkd_cooperative-1.0.3.dist-info/top_level.txt
rkd_cooperative-1.0.3.dist-info/RECORD
