Metadata-Version: 2.1
Name: rkd-cooperative
Version: 1.0.3
Summary: Simple snippet manager (similar to package manager) with JINJA2 templating and interactive installation Wizard support!
Home-page: https://riotkit.org
Author: RiotKit non-profit organization
Author-email: riotkit@riseup.net
License: Apache-2
Keywords: rkd,cooperative,appstore,store,snippet,snippetstore
Platform: UNKNOWN
Classifier: Development Status :: 5 - Production/Stable
Classifier: Environment :: Console
Classifier: Intended Audience :: System Administrators
Classifier: Intended Audience :: Developers
Classifier: Intended Audience :: Information Technology
Classifier: Intended Audience :: Other Audience
Classifier: Natural Language :: English
Classifier: License :: OSI Approved :: Apache Software License
Classifier: Operating System :: OS Independent
Classifier: Topic :: System :: Installation/Setup
Classifier: Topic :: System :: Systems Administration
Classifier: Programming Language :: Python
Requires-Dist: rkd (>=2.3.4)
